jsondiff/__init__.py
jsondiff/cli.py
jsondiff/symbols.py
jsondiff2-1.2.3.dist-info/LICENSE
jsondiff2-1.2.3.dist-info/METADATA
jsondiff2-1.2.3.dist-info/WHEEL
jsondiff2-1.2.3.dist-info/entry_points.txt
jsondiff2-1.2.3.dist-info/top_level.txt
jsondiff2-1.2.3.dist-info/RECORD
