Metadata-Version: 2.1
Name: jsondiff2
Version: 1.2.3
Summary: Diff JSON and JSON-like structures in Python
Home-page: https://github.com/edoreld/jsondiff
Author: Javier Martinez
Author-email: edoreld@gmail.com
License: UNKNOWN
Keywords: json,diff,diffing,difference,patch,delta,dict,LCS
Platform: UNKNOWN
Classifier: Programming Language :: Python :: 2
Classifier: Programming Language :: Python :: 2.7
Classifier: Programming Language :: Python :: 3
